aiknow/__init__.py
aiknow/db/__init__.py
aiknow/llm/__init__.py
aiknow/llm/auth.py
aiknow/llm/chat/__init__.py
aiknow/llm/chat/message.py
aiknow/llm/chat/model.py
aiknow/llm/chat/response.py
aiknow/llm/embedding/__init__.py
aiknow/llm/openai/__init__.py
aiknow/llm/openai/auth.py
aiknow/llm/openai/chat.py
aiknow/llm/openai/response.py
aiknow/llm/qianfan/__init__.py
aiknow/llm/qianfan/auth.py
aiknow/llm/qianfan/chat.py
aiknow/llm/qianfan/response.py
aiknow-0.0.3.dist-info/METADATA
aiknow-0.0.3.dist-info/WHEEL
aiknow-0.0.3.dist-info/RECORD
