Metadata-Version: 2.1
Name: aiknow
Version: 0.0.3
Summary: 
Author: isaac-fei
Author-email: isaac.omega.fei@gmail.com
Requires-Python: >=3.11,<4.0
Classifier: Programming Language :: Python :: 3
Classifier: Programming Language :: Python :: 3.11
Requires-Dist: openai (>=1.6.1,<2.0.0)
Requires-Dist: pydantic (>=2.5.3,<3.0.0)
Requires-Dist: pydantic-settings (>=2.1.0,<3.0.0)
Requires-Dist: qianfan (>=0.2.5,<0.3.0)
